OpentronsHTTPAPIWrapper/__init__.py
OpentronsHTTPAPIWrapper/opentronsHTTPAPI_clientBuilder.py
opentronshttpapiwrapper-0.0.3.dist-info/licenses/LICENSE
opentronshttpapiwrapper-0.0.3.dist-info/METADATA
opentronshttpapiwrapper-0.0.3.dist-info/WHEEL
opentronshttpapiwrapper-0.0.3.dist-info/top_level.txt
opentronshttpapiwrapper-0.0.3.dist-info/RECORD
