Metadata-Version: 2.4
Name: OpentronsHTTPAPIWrapper
Version: 0.0.3
Summary: Python wrapper for the opentrons http api.
Home-page: https://github.com/yourusername/my_project
Author: Daniel Persaud, Nis Fisker-Bødker
License: CC0-1.0
Project-URL: Homepage, https://github.com/dpersaud/opentronsHTTPAPI_wrapper
Project-URL: Repository, https://github.com/dpersaud/opentronsHTTPAPI_wrapper
Requires-Python: >=3.8
License-File: LICENSE
Requires-Dist: requests
Dynamic: home-page
Dynamic: license-file
Dynamic: requires-python
